PrinterService/__init__.py
PrinterService/__main__.py
PrinterService/api.py
PrinterService/const.py
PrinterService/service.py
pih_printer-1.13.dist-info/METADATA
pih_printer-1.13.dist-info/WHEEL
pih_printer-1.13.dist-info/entry_points.txt
pih_printer-1.13.dist-info/top_level.txt
pih_printer-1.13.dist-info/RECORD
