Metadata-Version: 2.1
Name: pih-printer
Version: 1.13
Summary: PIH Printer service package
Home-page: https://pacifichosp.com/
Author: Nikita Karachentsev
Author-email: it@pacifichosp.com
License: MIT
Requires-Dist: ipih
Requires-Dist: pyasn1 ==0.4.8
Requires-Dist: pycryptodomex ==3.15.0
Requires-Dist: pysmi ==0.3.4
Requires-Dist: pysnmp
